{
    "Bloom Taxonomy": {
        "Remember": [
            {
                "Original Question": "Qu'est-ce qu'une onde mécanique ? Donnez une définition concise.",
                "Sub-Question": {
                    "Question": "What is the definition of a mechanical wave?",
                    "Answer": "sdfgsdg"
                }
            },
            {
                "Original Question": "Comment la vitesse de propagation d'une onde est-elle définie dans un milieu ? Utilisez la formule donnée dans vos notes.",
                "Sub-Question": {
                    "Question": "Recall the formula used to define the speed of wave propagation in a medium.",
                    "Answer": ""
                }
            },
            {
                "Original Question": "Si une onde sonore nécessite un milieu matériel pour se propager, pourquoi le son ne se propage-t-il pas dans le vide ?",
                "Sub-Question": {
                    "Question": "Why does sound require a material medium to propagate?",
                    "Answer": "sdgsdg"
                }
            },
            {
                "Original Question": "Qu'est-ce que le principe de superposition pour les ondes mécaniques ? Illustrer par un exemple simple ce que cela signifie lorsque deux ondes se rencontrent.",
                "Sub-Question": {
                    "Question": "Define the principle of superposition for mechanical waves.",
                    "Answer": ""
                }
            },
            {
                "Original Question": "En utilisant la relation V=dΔtV=Δtd​, calculez la célérité d’une onde si la distance parcourue est de 340 mètres et le temps pris est de 1 seconde.",
                "Sub-Question": {
                    "Question": "Recall the formula V=dΔtV=Δtd​ used to calculate wave velocity.",
                    "Answer": ""
                }
            },
            {
                "Original Question": "Si le retard ττ est la différence de temps pour que l'onde atteigne deux points différents dans le milieu, comment calculeriez-vous le retard entre deux points situés à 170 mètres l'un de l'autre, si la vitesse de l'onde est de 340 m/s ?",
                "Sub-Question": {
                    "Question": "Define the concept of wave delay or retard in wave propagation.",
                    "Answer": ""
                }
            }
        ],
        "Understand": [
            {
                "Original Question": "Qu'est-ce qu'une onde mécanique ? Donnez une définition concise.",
                "Sub-Question": {
                    "Question": "Explain the concept of a mechanical wave in your own words.",
                    "Answer": ""
                }
            },
            {
                "Original Question": "Comment la vitesse de propagation d'une onde est-elle définie dans un milieu ? Utilisez la formule donnée dans vos notes.",
                "Sub-Question": {
                    "Question": "Explain the relationship between wave speed and medium properties.",
                    "Answer": ""
                }
            },
            {
                "Original Question": "Si une onde sonore nécessite un milieu matériel pour se propager, pourquoi le son ne se propage-t-il pas dans le vide ?",
                "Sub-Question": {
                    "Question": "Explain the concept of sound waves and their dependence on a medium.",
                    "Answer": ""
                }
            },
            {
                "Original Question": "Qu'est-ce que le principe de superposition pour les ondes mécaniques ? Illustrer par un exemple simple ce que cela signifie lorsque deux ondes se rencontrent.",
                "Sub-Question": {
                    "Question": "Explain how the principle of superposition applies to wave interactions.",
                    "Answer": ""
                }
            },
            {
                "Original Question": "En utilisant la relation V=dΔtV=Δtd​, calculez la célérité d’une onde si la distance parcourue est de 340 mètres et le temps pris est de 1 seconde.",
                "Sub-Question": {
                    "Question": "Explain how distance and time are related to wave velocity in the given formula.",
                    "Answer": ""
                }
            },
            {
                "Original Question": "Si le retard ττ est la différence de temps pour que l'onde atteigne deux points différents dans le milieu, comment calculeriez-vous le retard entre deux points situés à 170 mètres l'un de l'autre, si la vitesse de l'onde est de 340 m/s ?",
                "Sub-Question": {
                    "Question": "Explain how wave delay is calculated between two points in a medium.",
                    "Answer": ""
                }
            }
        ],
        "Apply": [
            {
                "Original Question": "Qu'est-ce qu'une onde mécanique ? Donnez une définition concise.",
                "Sub-Question": {
                    "Question": "How would you identify a mechanical wave in a given scenario?",
                    "Answer": ""
                }
            },
            {
                "Original Question": "Comment la vitesse de propagation d'une onde est-elle définie dans un milieu ? Utilisez la formule donnée dans vos notes.",
                "Sub-Question": {
                    "Question": "Calculate the speed of a wave given specific medium characteristics.",
                    "Answer": ""
                }
            },
            {
                "Original Question": "Si une onde sonore nécessite un milieu matériel pour se propager, pourquoi le son ne se propage-t-il pas dans le vide ?",
                "Sub-Question": {
                    "Question": "How would you demonstrate the absence of sound propagation in a vacuum?",
                    "Answer": ""
                }
            },
            {
                "Original Question": "Qu'est-ce que le principe de superposition pour les ondes mécaniques ? Illustrer par un exemple simple ce que cela signifie lorsque deux ondes se rencontrent.",
                "Sub-Question": {
                    "Question": "How would you apply the principle of superposition to analyze wave interference?",
                    "Answer": ""
                }
            },
            {
                "Original Question": "En utilisant la relation V=dΔtV=Δtd​, calculez la célérité d’une onde si la distance parcourue est de 340 mètres et le temps pris est de 1 seconde.",
                "Sub-Question": {
                    "Question": "Calculate the velocity of a wave using the provided formula and values.",
                    "Answer": ""
                }
            },
            {
                "Original Question": "Si le retard ττ est la différence de temps pour que l'onde atteigne deux points différents dans le milieu, comment calculeriez-vous le retard entre deux points situés à 170 mètres l'un de l'autre, si la vitesse de l'onde est de 340 m/s ?",
                "Sub-Question": {
                    "Question": "Calculate the delay between two points given the distance and wave speed.",
                    "Answer": ""
                }
            }
        ],
        "Analyze": [
            {
                "Original Question": "Qu'est-ce qu'une onde mécanique ? Donnez une définition concise.",
                "Sub-Question": {
                    "Question": "Break down the components of a mechanical wave and how they interact.",
                    "Answer": ""
                }
            },
            {
                "Original Question": "Comment la vitesse de propagation d'une onde est-elle définie dans un milieu ? Utilisez la formule donnée dans vos notes.",
                "Sub-Question": {
                    "Question": "Examine how different medium properties affect wave propagation speeds.",
                    "Answer": ""
                }
            },
            {
                "Original Question": "Si une onde sonore nécessite un milieu matériel pour se propager, pourquoi le son ne se propage-t-il pas dans le vide ?",
                "Sub-Question": {
                    "Question": "Investigate the properties of sound waves that prevent propagation in a vacuum.",
                    "Answer": ""
                }
            },
            {
                "Original Question": "Qu'est-ce que le principe de superposition pour les ondes mécaniques ? Illustrer par un exemple simple ce que cela signifie lorsque deux ondes se rencontrent.",
                "Sub-Question": {
                    "Question": "Break down the effects of superposition when waves meet and interact.",
                    "Answer": ""
                }
            },
            {
                "Original Question": "En utilisant la relation V=dΔtV=Δtd​, calculez la célérité d’une onde si la distance parcourue est de 340 mètres et le temps pris est de 1 seconde.",
                "Sub-Question": {
                    "Question": "Analyze the factors influencing wave velocity calculations.",
                    "Answer": "sdgsdg"
                }
            },
            {
                "Original Question": "Si le retard ττ est la différence de temps pour que l'onde atteigne deux points différents dans le milieu, comment calculeriez-vous le retard entre deux points situés à 170 mètres l'un de l'autre, si la vitesse de l'onde est de 340 m/s ?",
                "Sub-Question": {
                    "Question": "Analyze the relationship between distance, wave speed, and wave delay.",
                    "Answer": ""
                }
            }
        ],
        "Evaluate": [
            {
                "Original Question": "Qu'est-ce qu'une onde mécanique ? Donnez une définition concise.",
                "Sub-Question": {
                    "Question": "Judge the effectiveness of using mechanical waves in various applications.",
                    "Answer": "sdgsdg"
                }
            },
            {
                "Original Question": "Comment la vitesse de propagation d'une onde est-elle définie dans un milieu ? Utilisez la formule donnée dans vos notes.",
                "Sub-Question": {
                    "Question": "Assess the impact of medium elasticity on wave velocity.",
                    "Answer": ""
                }
            },
            {
                "Original Question": "Si une onde sonore nécessite un milieu matériel pour se propager, pourquoi le son ne se propage-t-il pas dans le vide ?",
                "Sub-Question": {
                    "Question": "Judge the implications of sound wave behavior in different mediums.",
                    "Answer": ""
                }
            },
            {
                "Original Question": "Qu'est-ce que le principe de superposition pour les ondes mécaniques ? Illustrer par un exemple simple ce que cela signifie lorsque deux ondes se rencontrent.",
                "Sub-Question": {
                    "Question": "Assess the importance of understanding superposition in wave phenomena.",
                    "Answer": "sdgsdg"
                }
            },
            {
                "Original Question": "En utilisant la relation V=dΔtV=Δtd​, calculez la célérité d’une onde si la distance parcourue est de 340 mètres et le temps pris est de 1 seconde.",
                "Sub-Question": {
                    "Question": "Evaluate the accuracy of the calculated wave velocity in a real-world scenario.",
                    "Answer": ""
                }
            },
            {
                "Original Question": "Si le retard ττ est la différence de temps pour que l'onde atteigne deux points différents dans le milieu, comment calculeriez-vous le retard entre deux points situés à 170 mètres l'un de l'autre, si la vitesse de l'onde est de 340 m/s ?",
                "Sub-Question": {
                    "Question": "Evaluate the significance of wave delay in communication systems.",
                    "Answer": ""
                }
            }
        ],
        "Create": [
            {
                "Original Question": "Qu'est-ce qu'une onde mécanique ? Donnez une définition concise.",
                "Sub-Question": {
                    "Question": "Develop a model to demonstrate the propagation of a mechanical wave.",
                    "Answer": ""
                }
            },
            {
                "Original Question": "Comment la vitesse de propagation d'une onde est-elle définie dans un milieu ? Utilisez la formule donnée dans vos notes.",
                "Sub-Question": {
                    "Question": "Design an experiment to measure the speed of wave propagation in different mediums.",
                    "Answer": ""
                }
            },
            {
                "Original Question": "Si une onde sonore nécessite un milieu matériel pour se propager, pourquoi le son ne se propage-t-il pas dans le vide ?",
                "Sub-Question": {
                    "Question": "Propose a solution to enable sound transmission in a vacuum environment.",
                    "Answer": "sdgsdg"
                }
            },
            {
                "Original Question": "Qu'est-ce que le principe de superposition pour les ondes mécaniques ? Illustrer par un exemple simple ce que cela signifie lorsque deux ondes se rencontrent.",
                "Sub-Question": {
                    "Question": "Create a simulation showing the superposition of two mechanical waves.",
                    "Answer": ""
                }
            },
            {
                "Original Question": "En utilisant la relation V=dΔtV=Δtd​, calculez la célérité d’une onde si la distance parcourue est de 340 mètres et le temps pris est de 1 seconde.",
                "Sub-Question": {
                    "Question": "Devise a scenario where measuring wave velocity is crucial for decision-making.",
                    "Answer": ""
                }
            },
            {
                "Original Question": "Si le retard ττ est la différence de temps pour que l'onde atteigne deux points différents dans le milieu, comment calculeriez-vous le retard entre deux points situés à 170 mètres l'un de l'autre, si la vitesse de l'onde est de 340 m/s ?",
                "Sub-Question": {
                    "Question": "Design a system that compensates for wave delays in a communication network.",
                    "Answer": ""
                }
            }
        ]
    }
}